Metadata-Version: 2.1
Name: imagefilterai
Version: 23.2.10
Summary: Important image editing functions such as applying a black and white filter, deleting the background of images, a “cartoon” filter, and others.
Author: Igor_Shapovalov_Andrejovich
Author-email: igor.shapovalov.andrejovich@gmail.com
